MANIFEST.in
README.txt
sbdart.py
setup.py
PySBdart.egg-info/PKG-INFO
PySBdart.egg-info/SOURCES.txt
PySBdart.egg-info/dependency_links.txt
PySBdart.egg-info/top_level.txt
fsource/Makefile
fsource/Makefile~
fsource/atms.f
fsource/disort.f
fsource/disutil.f
fsource/drt.f
fsource/fMakefile~
fsource/iMakefile~
fsource/params.f
fsource/sbdart
fsource/spectra.f
fsource/tauaero.f
fsource/taucloud.f
fsource/taugas.f
sbouts/sbout.1
sbouts/sbout.2
sbouts/sbout.3
sbouts/sbout.4
sbouts/sbout.5
test/test_sbdart.py