Metadata-Version: 1.0
Name: PySBdart
Version: 0.0.9
Summary: Numerical Computations
Home-page: UNKNOWN
Author: Philip Schleihauf
Author-email: uniphil@gmail.com
License: Public Domain
Platform: UNKNOWN
